fseai/__init__.py
fseai/fseai_models.py
fseai/vision.py
fseai-0.0.2.dist-info/LICENSE
fseai-0.0.2.dist-info/METADATA
fseai-0.0.2.dist-info/WHEEL
fseai-0.0.2.dist-info/top_level.txt
fseai-0.0.2.dist-info/RECORD
