Metadata-Version: 2.1
Name: fseai
Version: 0.0.2
Summary: Full Stack Engineering AI course package
Home-page: UNKNOWN
Author: Hanoona Rasheed
Author-email: hanoona.rasheed@inkerrobotics.com
License: UNKNOWN
Platform: UNKNOWN
Classifier: Development Status :: 2 - Pre-Alpha
Classifier: Intended Audience :: Education
Classifier: License :: OSI Approved :: Apache Software License
Classifier: Natural Language :: English
Classifier: Operating System :: OS Independent
Classifier: Operating System :: Microsoft :: Windows :: Windows 10
Classifier: Environment :: Win32 (MS Windows)
Classifier: Programming Language :: Python :: 3 :: Only
Classifier: Programming Language :: Python :: 3
Classifier: Programming Language :: Python :: 3.6
Classifier: Programming Language :: Python :: 3.7
Classifier: Topic :: Scientific/Engineering
Classifier: Topic :: Utilities
Classifier: Topic :: Scientific/Engineering :: Artificial Intelligence
Requires-Python: >=3.6
Requires-Dist: torch (>=1.6.0)
Requires-Dist: matplotlib
Requires-Dist: torchvision (>=0.7.0)
